openbes/__init__.py
openbes/examples.py
openbes/example_data/holywell_house.json
openbes/schemas/OpenBES.schema.json
openbes/schemas/__init__.py
openbes/schemas/conversion/__init__.py
openbes/schemas/conversion/json_to_toml.py
openbes/schemas/conversion/toml_to_json.py
openbes/schemas/generated/__init__.py
openbes/schemas/generated/models.py
openbes/simulations/__init__.py
openbes/simulations/base.py
openbes/simulations/building_energy.py
openbes/simulations/climate.py
openbes/simulations/cooling.py
openbes/simulations/geometry.py
openbes/simulations/heating.py
openbes/simulations/hot_water.py
openbes/simulations/lighting.py
openbes/simulations/occupancy.py
openbes/simulations/solar_irradiation.py
openbes/simulations/ventilation.py
openbes/simulations/climate_data/SPAIN_Madrid.082210_SWEC.epw
openbes/simulations/climate_data/SPAIN_Sevilla.083910_SWEC.epw
openbes/simulations/climate_data/UK_Oxford_COLBE_50th_4550210_TRY_2080s.epw
openbes/simulations/climate_data/UK_Oxford_GBR_ENG_RAF.Benson.036580_TMYx.2007-2021.epw
openbes/simulations/climate_data/UK_Oxford_POWER_point_hourly_AMY_2023.epw
openbes/simulations/climate_data/UK_Oxford_Prometheus_a1b_50_percentile_TRY_2050.epw
openbes/simulations/climate_data/USA_Denver_725650TYCST.epw
openbes/simulations/lighting_data/lamp_fc.csv
openbes/simulations/lighting_data/lamp_ft_t5.csv
openbes/simulations/lighting_data/lamp_ft_t8.csv
openbes/simulations/lighting_data/lamp_ft_t8_be.csv
openbes/simulations/lighting_data/lamp_im.csv
openbes/simulations/lighting_data/lamp_ind.csv
openbes/simulations/lighting_data/lamp_vm.csv
openbes/simulations/lighting_data/lamp_vs.csv
openbes/types/__init__.py
openbes/types/dataclasses.py
openbes/types/enums.py
openbes-0.2.0.dist-info/METADATA
openbes-0.2.0.dist-info/WHEEL
openbes-0.2.0.dist-info/top_level.txt
openbes-0.2.0.dist-info/RECORD
