Metadata-Version: 2.4
Name: openBES
Version: 0.2.0
Summary: Python implementation of the Open Building Energy Simulation (OpenBES) tool.
Requires-Python: >=3.11
Requires-Dist: numpy>=2
Requires-Dist: pandas
Requires-Dist: pvlib
Requires-Dist: pydantic>=2.7
Provides-Extra: jit
Requires-Dist: numba; extra == "jit"
Provides-Extra: dev
Requires-Dist: line_profiler; extra == "dev"
Requires-Dist: numba; extra == "dev"
Requires-Dist: datamodel-code-generator>=0.43; extra == "dev"
Requires-Dist: ruff; extra == "dev"
Requires-Dist: jsonschema>=4; extra == "dev"
